pyextrica/__init__.py
pyextrica/_version.py
pyextrica/auth.py
pyextrica/client.py
pyextrica/constants.py
pyextrica/dbapi.py
pyextrica/exceptions.py
pyextrica/extrica_rest_handler.py
pyextrica/logging.py
pyextrica/pyextrica_functions.py
pyextrica/query_parser.py
pyextrica/transaction.py
pyextrica/sqlalchemy/__init__.py
pyextrica/sqlalchemy/compiler.py
pyextrica/sqlalchemy/datatype.py
pyextrica/sqlalchemy/dialect.py
pyextrica/sqlalchemy/error.py
pyextrica/sqlalchemy/util.py
pyextrica-17.2.2.dist-info/METADATA
pyextrica-17.2.2.dist-info/WHEEL
pyextrica-17.2.2.dist-info/entry_points.txt
pyextrica-17.2.2.dist-info/top_level.txt
pyextrica-17.2.2.dist-info/RECORD
