Metadata-Version: 2.1
Name: pyextrica
Version: 17.2.2
Summary: Python client library for Extrica
Home-page: https://github.com/extricatrianz/pyextrica
Author: Extrica Team
Author-email: extricaproductionsupport@trianz.com
Classifier: Development Status :: 4 - Beta
Classifier: Intended Audience :: Developers
Classifier: License :: OSI Approved :: Apache Software License
Classifier: Operating System :: MacOS :: MacOS X
Classifier: Operating System :: POSIX
Classifier: Operating System :: Microsoft :: Windows
Classifier: Programming Language :: Python
Classifier: Programming Language :: Python :: 3
Classifier: Programming Language :: Python :: 3.8
Classifier: Programming Language :: Python :: 3.9
Classifier: Programming Language :: Python :: 3.10
Classifier: Programming Language :: Python :: 3.11
Classifier: Programming Language :: Python :: 3.12
Classifier: Programming Language :: Python :: Implementation :: CPython
Classifier: Programming Language :: Python :: Implementation :: PyPy
Classifier: Topic :: Database :: Front-Ends
Requires-Python: >=3.8
Requires-Dist: python-dateutil
Requires-Dist: pytz
Requires-Dist: requests (>=2.31.0)
Requires-Dist: tzlocal
Requires-Dist: sqlalchemy (>=1.3)
Requires-Dist: sql-metadata (==2.11.0)
Requires-Dist: backports.zoneinfo ; python_version < "3.9"
Provides-Extra: all
Requires-Dist: requests-kerberos ; extra == 'all'
Requires-Dist: sqlalchemy (>=1.3) ; extra == 'all'
Provides-Extra: external-authentication-token-cache
Requires-Dist: keyring ; extra == 'external-authentication-token-cache'
Provides-Extra: kerberos
Requires-Dist: requests-kerberos ; extra == 'kerberos'
Provides-Extra: sqlalchemy
Requires-Dist: sqlalchemy (>=1.3) ; extra == 'sqlalchemy'
Provides-Extra: tests
Requires-Dist: requests-kerberos ; extra == 'tests'
Requires-Dist: sqlalchemy (>=1.3) ; extra == 'tests'
Requires-Dist: httpretty (<1.1) ; extra == 'tests'
Requires-Dist: pytest ; extra == 'tests'
Requires-Dist: pytest-runner ; extra == 'tests'
Requires-Dist: pre-commit ; extra == 'tests'
Requires-Dist: black ; extra == 'tests'
Requires-Dist: isort ; extra == 'tests'
